pymlt/__init__.py
pymlt/aa_evaluate_grafana.py
pymlt/aa_evaluate_model.py
pymlt/aa_evaluate_shap.py
pymlt/aa_explore.py
pymlt/aa_load.py
pymlt/aa_model.py
pymlt/aa_transform.py
pymlt/config.py
pymlt/data_processing.py
pymlt/evaluate.py
pymlt/evaluate_datacamp.py
pymlt/explore.py
pymlt/explore_data_understanding.py
pymlt/features_datacamp.py
pymlt/load.py
pymlt/mi_data_cleaning.py
pymlt/mi_data_exploration.py
pymlt/mi_feature_engineering.py
pymlt/mi_feature_selection.py
pymlt/mi_modeling.py
pymlt/mi_pipeline_decorator.py
pymlt/mi_predict_model.py
pymlt/mi_train_model.py
pymlt/model.py
pymlt/model_train.py
pymlt/transform.py
pymlt/utils.py
pymlt-3.0.5.post0.dist-info/licenses/LICENSE
pymlt-3.0.5.post0.dist-info/METADATA
pymlt-3.0.5.post0.dist-info/WHEEL
pymlt-3.0.5.post0.dist-info/top_level.txt
pymlt-3.0.5.post0.dist-info/RECORD
