Metadata-Version: 2.4
Name: pymlt
Version: 3.0.5.post0
Summary: Python Machine Learning Toolkit
Author-email: Ben van Vliet <benvliet@icloud.com>
License: MIT
Project-URL: repository, https://github.com/benvliet/pymlt
Project-URL: issues, https://github.com/benvliet/pymlt/issues
Project-URL: homepage, https://pypi.org/project/pymlt/
Keywords: pymlt,machine learning,data science,toolkit,python
Classifier: Intended Audience :: Developers
Classifier: License :: OSI Approved :: MIT License
Classifier: Natural Language :: English
Classifier: Programming Language :: Python :: 3
Classifier: Programming Language :: Python :: 3.12
Requires-Python: >=3.7
License-File: LICENSE
Provides-Extra: test
Requires-Dist: pytest>=6.0; extra == "test"
Dynamic: license-file
